{
  "900" : {
    "http_status_code": 400,
    "message": "Ошибка декодирования запроса"
  },
  "901" : {
    "http_status_code": 400,
    "message": "Username содержит ошибки"
  },
  "902" : {
    "http_status_code": 400,
    "message": "Email содержит ошибки"
  },
  "903" : {
    "http_status_code": 400,
    "message": "Пользователь уже существует"
  },
  "904" : {
    "http_status_code": 404,
    "message": "Аккаунт не найден"
  },
  "905" : {
    "http_status_code": 401,
    "message": "Неверный пароль"
  },
  "906" : {
    "http_status_code": 401,
    "message": "Аккаунт заблокирован"
  },
  "907" : {
    "http_status_code": 401,
    "message": "Аккаунт не активирован"
  },
  "908" : {
    "http_status_code": 403,
    "message": "Не аутентифицирован"
  },
  "909" : {
    "http_status_code": 403,
    "message": "Not permission"
  },
  "910" : {
    "http_status_code": 401,
    "message": "Не авторизован"
  },
  "911" : {
    "http_status_code": 400,
    "message": "Неправильный код подтверждения"
  },
  "912" : {
    "http_status_code": 400,
    "message": "Уже подтвержден"
  },
  "913" : {
    "http_status_code": 400,
    "message": "Время подтверждения истекло"
  },
  "914" : {
    "http_status_code": 400,
    "message": "Время подтверждения ещё не истекло"
  },
  "915" : {
    "http_status_code": 400,
    "message": "Сначала отправьте код подтверждения"
  },
  "916" : {
    "http_status_code": 400,
    "message": "Превышено количество попыток. Отправьте код повторно"
  },
  "917" : {
    "http_status_code": 404,
    "message": "Публикация не найдена"
  },
  "918" : {
    "http_status_code": 401,
    "message": "Невозможно запросить больше 100 публикаций за раз"
  },
  "919" : {
    "http_status_code": 404,
    "message": "Не найден"
  },
  "920" : {
    "http_status_code": 401,
    "message": "Уже авторизован"
  },
  "921" : {
    "http_status_code": 400,
    "message": "Password содержит ошибки"
  },
   "922" : {
    "http_status_code": 400,
    "message": "Email уже зарегистрирован"
  }
}
